pyirecovery/__init__.py
pyirecovery/__main__.py
pyirecovery/no_backend_fix.py
pyirecovery-0.1.6.dist-info/LICENSE
pyirecovery-0.1.6.dist-info/METADATA
pyirecovery-0.1.6.dist-info/WHEEL
pyirecovery-0.1.6.dist-info/entry_points.txt
pyirecovery-0.1.6.dist-info/RECORD
